sunnybeamtool/__init__.py
sunnybeamtool/sunnybeamtool.py
sunnybeamtool2-0.1.0.dist-info/LICENSE
sunnybeamtool2-0.1.0.dist-info/METADATA
sunnybeamtool2-0.1.0.dist-info/WHEEL
sunnybeamtool2-0.1.0.dist-info/top_level.txt
sunnybeamtool2-0.1.0.dist-info/RECORD
